{
  "collectionName": "components_site_components_split_hero_columns",
  "info": {
    "displayName": "split-hero-column",
    "icon": "layout"
  },
  "options": {},
  "attributes": {
    "type": {
      "type": "enumeration",
      "required": true,
      "default": "none",
      "enum": [
        "none",
        "imageCollection",
        "singleImage",
        "floatingImages",
        "textBlock",
        "form"
      ]
    },
    "textBlock": {
      "type": "component",
      "conditions": {
        "visible": {
          "==": [
            {
              "var": "type"
            },
            "textBlock"
          ]
        }
      },
      "component": "site-components.normal-hero-section",
      "repeatable": false,
      "required": true
    },
    "form": {
      "type": "component",
      "conditions": {
        "visible": {
          "==": [
            {
              "var": "type"
            },
            "form"
          ]
        }
      },
      "component": "site-components.iframe-form",
      "repeatable": false,
      "required": true
    },
    "singleImage": {
      "type": "component",
      "conditions": {
        "visible": {
          "==": [
            {
              "var": "type"
            },
            "singleImage"
          ]
        }
      },
      "component": "site-components.single-image",
      "repeatable": false,
      "required": true
    },
    "floatingImages": {
      "type": "component",
      "conditions": {
        "visible": {
          "==": [
            {
              "var": "type"
            },
            "floatingImages"
          ]
        }
      },
      "component": "site-components.floating-images",
      "repeatable": false,
      "required": true
    },
    "imageCollection": {
      "type": "component",
      "conditions": {
        "visible": {
          "==": [
            {
              "var": "type"
            },
            "imageCollection"
          ]
        }
      },
      "component": "site-components.image-collection",
      "repeatable": false,
      "required": true
    }
  },
  "config": {}
}
